ansatz/__init__.py
ansatz/base.py
ansatz/custom_ansatz.py
ansatz/he_ansatz.py
ansatz/uccds_ansatz.py
ansatz/upccgsd_ansatz.py
beginstate/__init__.py
beginstate/beginstate.py
lattice/__init__.py
lattice/lattice.py
optimizers/__init__.py
optimizers/adap_opt.py
optimizers/gradient_opt.py
optimizers/scipy_opt.py
variational/__init__.py
variational/adapt/__init__.py
variational/adapt/base.py
variational/adapt/fermihubbard.py
variational/adapt/molecular.py
variational/struct/__init__.py
variational/struct/struct.py
variational/vqe/__init__.py
variational/vqe/base.py
variational/vqe/fermihubbard.py
variational/vqe/molecular.py
variational/vqe/spin.py
vqesimulation-1.0.0.dist-info/LICENCE.txt
vqesimulation-1.0.0.dist-info/METADATA
vqesimulation-1.0.0.dist-info/WHEEL
vqesimulation-1.0.0.dist-info/top_level.txt
vqesimulation-1.0.0.dist-info/RECORD
