Metadata-Version: 2.1
Name: vqesimulation
Version: 1.0.0
Summary: Paquete para construir hamiltonianos y ejecutar el VQE
Home-page: https://github.com/javinoram/vqesimulation
Author: Javier Norambuena Leiva
Author-email: javier.norambuenal@sansano.usm.cl
Classifier: Programming Language :: Python :: 3
Classifier: License :: OSI Approved :: MIT License
Classifier: Operating System :: OS Independent
Requires-Python: >=3.9
License-File: LICENCE.txt
